ott_platform/__init__.py
ott_platform/ott_platform.py
ott_platform-0.1.dist-info/METADATA
ott_platform-0.1.dist-info/WHEEL
ott_platform-0.1.dist-info/license.txt
ott_platform-0.1.dist-info/top_level.txt
ott_platform-0.1.dist-info/RECORD
