Metadata-Version: 2.1
Name: ott-platform
Version: 0.1
Summary: API package that provides us the method to creat an OTT like environment
Author: auth
Author-email: suryajeetwork@email.com
License: MIT
License-File: license.txt
Requires-Dist: pandas
Requires-Dist: requests
